timeSHIT/TimeSHIT_Filler.py
timeSHIT/__init__.py
timeSHIT/__main__.py
timeSHIT-0.0.3.dist-info/LICENSE
timeSHIT-0.0.3.dist-info/METADATA
timeSHIT-0.0.3.dist-info/WHEEL
timeSHIT-0.0.3.dist-info/entry_points.txt
timeSHIT-0.0.3.dist-info/top_level.txt
timeSHIT-0.0.3.dist-info/RECORD
