Metadata-Version: 2.1
Name: timeSHIT
Version: 0.0.3
Summary: Ease the pain of logging your time in JIRA timesheets
Home-page: https://github.com/Kaushal28/Timesheet-Filler.git
Author: kaushal28
Author-email: shah.kaushal95@gmail.com
License: UNKNOWN
Platform: UNKNOWN
Classifier: Programming Language :: Python :: 3
Classifier: License :: OSI Approved :: MIT License
Requires-Dist: schedule (==0.6.0)
